janusgraphy/__init__.py
janusgraphy/graph_object.py
janusgraphy/gremlin_python_interface.py
janusgraphy/helpers.py
janusgraphy/query.py
janusgraphy/traversal.py
janusgraphy-0.2.1.dist-info/WHEEL
janusgraphy-0.2.1.dist-info/METADATA
janusgraphy-0.2.1.dist-info/RECORD
