Metadata-Version: 2.1
Name: janusgraphy
Version: 0.2.1
Summary: 
Author: Victor Marcelino
Author-email: victor.fmarcelino@gmail.com
Requires-Python: >=3.6,<4.0
Classifier: Programming Language :: Python :: 3
Classifier: Programming Language :: Python :: 3.6
Classifier: Programming Language :: Python :: 3.7
Requires-Dist: gremlinpython (==3.2.9)
